AUTHORS
LICENSE
MANIFEST.in
README.rst
setup.py
django_undermythumb.egg-info/PKG-INFO
django_undermythumb.egg-info/SOURCES.txt
django_undermythumb.egg-info/dependency_links.txt
django_undermythumb.egg-info/top_level.txt
exampleproject/__init__.py
exampleproject/manage.py
exampleproject/settings.py
exampleproject/urls.py
exampleproject/blog/__init__.py
exampleproject/blog/admin.py
exampleproject/blog/models.py
exampleproject/blog/tests.py
exampleproject/blog/views.py
undermythumb/__init__.py
undermythumb/fields.py
undermythumb/files.py
undermythumb/models.py
undermythumb/renderers.py
undermythumb/thumbnails.py
undermythumb/management/__init__.py
undermythumb/management/commands/__init__.py
undermythumb/management/commands/createthumbnails.py
undermythumb/tests/__init__.py
undermythumb/tests/models.py
undermythumb/tests/run_tests.py
undermythumb/tests/statler_waldorf.jpg
undermythumb/tests/storage.py
undermythumb/tests/sweetums_lecture.jpg
undermythumb/tests/test_settings.py
undermythumb/tests/tests.py