Metadata-Version: 1.0
Name: django-undermythumb
Version: 0.2.3
Summary: The Django thumbnail generation package with a heart of stone.
Home-page: http://github.com/pitchfork/django-undermythumb/
Author: Pitchfork Media, Inc.
Author-email: dev@pitchfork.com
License: UNKNOWN
Platform: UNKNOWN
Classifier: Development Status :: 4 - Beta
Classifier: Environment :: Web Environment
Classifier: Intended Audience :: Developers
Classifier: License :: OSI Approved :: BSD License
Classifier: Operating System :: OS Independent
Classifier: Programming Language :: Python
Classifier: Framework :: Django
